pysigsci/__init__.py
pysigsci/powerrules/__init__.py
pysigsci/powerrules/powerrules.py
pysigsci/releases/__init__.py
pysigsci/releases/releases.py
pysigsci/sigsciapi/__init__.py
pysigsci/sigsciapi/sigsciapi.py
pysigsci-3.18.1.data/scripts/pysigsci
pysigsci-3.18.1.data/scripts/pysigscia
pysigsci-3.18.1.dist-info/LICENSE
pysigsci-3.18.1.dist-info/METADATA
pysigsci-3.18.1.dist-info/WHEEL
pysigsci-3.18.1.dist-info/top_level.txt
pysigsci-3.18.1.dist-info/RECORD
