Metadata-Version: 2.1
Name: pysigsci
Version: 3.18.1
Summary: A python wrapper for the Signal Sciences API - https://docs.signalsciences.net/api/
Home-page: https://github.com/foospidy/pysigsci
Download-URL: https://github.com/foospidy/pysigsci
Author: foospidy
License: MIT
Keywords: wrapper library signal sciences sigsci pysigsci api cli
Classifier: Intended Audience :: Developers
Classifier: Topic :: Software Development :: Libraries :: Python Modules
Classifier: Programming Language :: Python :: 2.7
Classifier: License :: OSI Approved :: MIT License
License-File: LICENSE
Requires-Dist: requests
Requires-Dist: pyopenssl
Requires-Dist: deepdiff
Requires-Dist: gitpython
